[
  {
    "title": "La Strada",
    "year": 1956
  },
  {
    "title": "The Nights of Cabiria",
    "year": 1957
  },
  {
    "title": "My Uncle",
    "year": 1958
  },
  {
    "title": "Black Orpheus",
    "year": 1959
  },
  {
    "title": "The Virgin Spring",
    "year": 1960
  },
  {
    "title": "Through a Glass Darkly",
    "year": 1961
  },
  {
    "title": "Sundays and Cybele",
    "year": 1962
  },
  {
    "title": "Federico Fellini's 8-1/2",
    "year": 1963
  },
  {
    "title": "Yesterday, Today and Tomorrow",
    "year": 1964
  },
  {
    "title": "The Shop on Main Street",
    "year": 1965
  },
  {
    "title": "A Man and a Woman",
    "year": 1966
  },
  {
    "title": "Closely Watched Trains",
    "year": 1967
  },
  {
    "title": "War and Peace",
    "year": 1968
  },
  {
    "title": "Z",
    "year": 1969
  },
  {
    "title": "Investigation of a Citizen above Suspicion",
    "year": 1970
  },
  {
    "title": "The Garden of the Finzi Continis",
    "year": 1971
  },
  {
    "title": "The Discreet Charm of the Bourgeoisie",
    "year": 1972
  },
  {
    "title": "Day for Night",
    "year": 1973
  },
  {
    "title": "Amarcord",
    "year": 1974
  },
  {
    "title": "Dersu Uzala",
    "year": 1975
  },
  {
    "title": "Black and White in Color",
    "year": 1976
  },
  {
    "title": "Madame Rosa",
    "year": 1977
  },
  {
    "title": "Get Out Your Handkerchiefs",
    "year": 1978
  },
  {
    "title": "The Tin Drum",
    "year": 1979
  },
  {
    "title": "Moscow Does Not Believe in Tears",
    "year": 1980
  },
  {
    "title": "Mephisto",
    "year": 1981
  },
  {
    "title": "Volver a Empezar ('To Begin Again')",
    "year": 1982
  },
  {
    "title": "Fanny & Alexander",
    "year": 1983
  },
  {
    "title": "Dangerous Moves",
    "year": 1984
  },
  {
    "title": "The Official Story",
    "year": 1985
  },
  {
    "title": "The Assault",
    "year": 1986
  },
  {
    "title": "Babette's Feast",
    "year": 1987
  },
  {
    "title": "Pelle the Conqueror",
    "year": 1988
  },
  {
    "title": "Cinema Paradiso",
    "year": 1989
  },
  {
    "title": "Journey of Hope",
    "year": 1990
  },
  {
    "title": "Mediterraneo",
    "year": 1991
  },
  {
    "title": "Indochine",
    "year": 1992
  },
  {
    "title": "Belle Epoque",
    "year": 1993
  },
  {
    "title": "Burnt by the Sun",
    "year": 1994
  },
  {
    "title": "Antonia's Line",
    "year": 1995
  },
  {
    "title": "Kolya",
    "year": 1996
  },
  {
    "title": "Character",
    "year": 1997
  },
  {
    "title": "Life Is Beautiful",
    "year": 1998
  },
  {
    "title": "All about My Mother",
    "year": 1999
  },
  {
    "title": "Crouching Tiger, Hidden Dragon",
    "year": 2000
  },
  {
    "title": "No Man's Land",
    "year": 2001
  },
  {
    "title": "Nowhere in Africa",
    "year": 2002
  },
  {
    "title": "The Barbarian Invasions",
    "year": 2003
  },
  {
    "title": "The Sea Inside",
    "year": 2004
  },
  {
    "title": "Tsotsi",
    "year": 2005
  },
  {
    "title": "The Lives of Others",
    "year": 2006
  },
  {
    "title": "The Counterfeiters",
    "year": 2007
  },
  {
    "title": "Departures",
    "year": 2008
  },
  {
    "title": "The Secret in Their Eyes",
    "year": 2009
  },
  {
    "title": "In a Better World",
    "year": 2010
  },
  {
    "title": "A Separation",
    "year": 2011
  },
  {
    "title": "Amour",
    "year": 2012
  },
  {
    "title": "The Great Beauty",
    "year": 2013
  },
  {
    "title": "Ida",
    "year": 2014
  },
  {
    "title": "Son of Saul",
    "year": 2015
  },
  {
    "title": "The Salesman",
    "year": 2016
  },
  {
    "title": "A Fantastic Woman",
    "year": 2017
  },
  {
    "title": "Roma",
    "year": 2018
  },
  {
    "title": "Parasite",
    "year": 2019
  },
  {
    "title": "Another Round",
    "year": 2020
  },
  {
    "title": "Drive My Car",
    "year": 2021
  },
  {
    "title": "All Quiet on the Western Front",
    "year": 2022
  },
  {
    "title": "The Zone of Interest",
    "year": 2023
  },
  {
    "title": "I'm Still Here",
    "year": 2024
  },
  {
    "title": "Sentimental Value",
    "year": 2025
  }
]
